{"id":4879511,"node_id":"MDEwOlJlcG9zaXRvcnk0ODc5NTEx","name":"msgpack-c","full_name":"msgpack/msgpack-c","private":false,"owner":{"login":"msgpack","id":198264,"node_id":"MDEyOk9yZ2FuaXphdGlvbjE5ODI2NA==","avatar_url":"https://avatars.githubusercontent.com/u/198264?v=4","gravatar_id":"","url":"https://api.github.com/users/msgpack","html_url":"https://github.com/msgpack","followers_url":"https://api.github.com/users/msgpack/followers","following_url":"https://api.github.com/users/msgpack/following{/other_user}","gists_url":"https://api.github.com/users/msgpack/gists{/gist_id}","starred_url":"https://api.github.com/users/msgpack/starred{/owner}{/repo}","subscriptions_url":"https://api.github.com/users/msgpack/subscriptions","organizations_url":"https://api.github.com/users/msgpack/orgs","repos_url":"https://api.github.com/users/msgpack/repos","events_url":"https://api.github.com/users/msgpack/events{/privacy}","received_events_url":"https://api.github.com/users/msgpack/received_events","type":"Organization","user_view_type":"public","site_admin":false},"html_url":"https://github.com/msgpack/msgpack-c","description":"MessagePack implementation for C and C++ / msgpack.org[C/C++]","fork":false,"url":"https://api.github.com/repos/msgpack/msgpack-c","forks_url":"https://api.github.com/repos/msgpack/msgpack-c/forks","keys_url":"https://api.github.com/repos/msgpack/msgpack-c/keys{/key_id}","collaborators_url":"https://api.github.com/repos/msgpack/msgpack-c/collaborators{/collaborator}","teams_url":"https://api.github.com/repos/msgpack/msgpack-c/teams","hooks_url":"https://api.github.com/repos/msgpack/msgpack-c/hooks","issue_events_url":"https://api.github.com/repos/msgpack/msgpack-c/issues/events{/number}","events_url":"https://api.github.com/repos/msgpack/msgpack-c/events","assignees_url":"https://api.github.com/repos/msgpack/msgpack-c/assignees{/user}","branches_url":"https://api.github.com/repos/msgpack/msgpack-c/branches{/branch}","tags_url":"https://api.github.com/repos/msgpack/msgpack-c/tags","blobs_url":"https://api.github.com/repos/msgpack/msgpack-c/git/blobs{/sha}","git_tags_url":"https://api.github.com/repos/msgpack/msgpack-c/git/tags{/sha}","git_refs_url":"https://api.github.com/repos/msgpack/msgpack-c/git/refs{/sha}","trees_url":"https://api.github.com/repos/msgpack/msgpack-c/git/trees{/sha}","statuses_url":"https://api.github.com/repos/msgpack/msgpack-c/statuses/{sha}","languages_url":"https://api.github.com/repos/msgpack/msgpack-c/languages","stargazers_url":"https://api.github.com/repos/msgpack/msgpack-c/stargazers","contributors_url":"https://api.github.com/repos/msgpack/msgpack-c/contributors","subscribers_url":"https://api.github.com/repos/msgpack/msgpack-c/subscribers","subscription_url":"https://api.github.com/repos/msgpack/msgpack-c/subscription","commits_url":"https://api.github.com/repos/msgpack/msgpack-c/commits{/sha}","git_commits_url":"https://api.github.com/repos/msgpack/msgpack-c/git/commits{/sha}","comments_url":"https://api.github.com/repos/msgpack/msgpack-c/comments{/number}","issue_comment_url":"https://api.github.com/repos/msgpack/msgpack-c/issues/comments{/number}","contents_url":"https://api.github.com/repos/msgpack/msgpack-c/contents/{+path}","compare_url":"https://api.github.com/repos/msgpack/msgpack-c/compare/{base}...{head}","merges_url":"https://api.github.com/repos/msgpack/msgpack-c/merges","archive_url":"https://api.github.com/repos/msgpack/msgpack-c/{archive_format}{/ref}","downloads_url":"https://api.github.com/repos/msgpack/msgpack-c/downloads","issues_url":"https://api.github.com/repos/msgpack/msgpack-c/issues{/number}","pulls_url":"https://api.github.com/repos/msgpack/msgpack-c/pulls{/number}","milestones_url":"https://api.github.com/repos/msgpack/msgpack-c/milestones{/number}","notifications_url":"https://api.github.com/repos/msgpack/msgpack-c/notifications{?since,all,participating}","labels_url":"https://api.github.com/repos/msgpack/msgpack-c/labels{/name}","releases_url":"https://api.github.com/repos/msgpack/msgpack-c/releases{/id}","deployments_url":"https://api.github.com/repos/msgpack/msgpack-c/deployments","created_at":"2012-07-04T01:46:16Z","updated_at":"2025-10-02T20:23:17Z","pushed_at":"2025-07-21T14:16:51Z","git_url":"git://github.com/msgpack/msgpack-c.git","ssh_url":"git@github.com:msgpack/msgpack-c.git","clone_url":"https://github.com/msgpack/msgpack-c.git","svn_url":"https://github.com/msgpack/msgpack-c","homepage":"","size":96604,"stargazers_count":3212,"watchers_count":3212,"language":null,"has_issues":true,"has_projects":true,"has_downloads":true,"has_wiki":true,"has_pages":true,"has_discussions":false,"forks_count":909,"mirror_url":null,"archived":false,"disabled":false,"open_issues_count":104,"license":{"key":"other","name":"Other","spdx_id":"NOASSERTION","url":null,"node_id":"MDc6TGljZW5zZTA="},"allow_forking":true,"is_template":false,"web_commit_signoff_required":false,"topics":[],"visibility":"public","forks":909,"open_issues":104,"watchers":3212,"default_branch":"master","permissions":{"admin":false,"maintain":false,"push":false,"triage":false,"pull":false},"temp_clone_token":"","custom_properties":{},"organization":{"login":"msgpack","id":198264,"node_id":"MDEyOk9yZ2FuaXphdGlvbjE5ODI2NA==","avatar_url":"https://avatars.githubusercontent.com/u/198264?v=4","gravatar_id":"","url":"https://api.github.com/users/msgpack","html_url":"https://github.com/msgpack","followers_url":"https://api.github.com/users/msgpack/followers","following_url":"https://api.github.com/users/msgpack/following{/other_user}","gists_url":"https://api.github.com/users/msgpack/gists{/gist_id}","starred_url":"https://api.github.com/users/msgpack/starred{/owner}{/repo}","subscriptions_url":"https://api.github.com/users/msgpack/subscriptions","organizations_url":"https://api.github.com/users/msgpack/orgs","repos_url":"https://api.github.com/users/msgpack/repos","events_url":"https://api.github.com/users/msgpack/events{/privacy}","received_events_url":"https://api.github.com/users/msgpack/received_events","type":"Organization","user_view_type":"public","site_admin":false},"network_count":909,"subscribers_count":154}