{"id":15896457,"node_id":"MDEwOlJlcG9zaXRvcnkxNTg5NjQ1Nw==","name":"Fast-CDR","full_name":"eProsima/Fast-CDR","private":false,"owner":{"login":"eProsima","id":6390783,"node_id":"MDEyOk9yZ2FuaXphdGlvbjYzOTA3ODM=","avatar_url":"https://avatars.githubusercontent.com/u/6390783?v=4","gravatar_id":"","url":"https://api.github.com/users/eProsima","html_url":"https://github.com/eProsima","followers_url":"https://api.github.com/users/eProsima/followers","following_url":"https://api.github.com/users/eProsima/following{/other_user}","gists_url":"https://api.github.com/users/eProsima/gists{/gist_id}","starred_url":"https://api.github.com/users/eProsima/starred{/owner}{/repo}","subscriptions_url":"https://api.github.com/users/eProsima/subscriptions","organizations_url":"https://api.github.com/users/eProsima/orgs","repos_url":"https://api.github.com/users/eProsima/repos","events_url":"https://api.github.com/users/eProsima/events{/privacy}","received_events_url":"https://api.github.com/users/eProsima/received_events","type":"Organization","site_admin":false},"html_url":"https://github.com/eProsima/Fast-CDR","description":"eProsima FastCDR library provides two serialization mechanisms. One is the standard CDR serialization mechanism, while the other is a faster implementation of it. Looking for commercial support? Contact info@eprosima.com","fork":false,"url":"https://api.github.com/repos/eProsima/Fast-CDR","forks_url":"https://api.github.com/repos/eProsima/Fast-CDR/forks","keys_url":"https://api.github.com/repos/eProsima/Fast-CDR/keys{/key_id}","collaborators_url":"https://api.github.com/repos/eProsima/Fast-CDR/collaborators{/collaborator}","teams_url":"https://api.github.com/repos/eProsima/Fast-CDR/teams","hooks_url":"https://api.github.com/repos/eProsima/Fast-CDR/hooks","issue_events_url":"https://api.github.com/repos/eProsima/Fast-CDR/issues/events{/number}","events_url":"https://api.github.com/repos/eProsima/Fast-CDR/events","assignees_url":"https://api.github.com/repos/eProsima/Fast-CDR/assignees{/user}","branches_url":"https://api.github.com/repos/eProsima/Fast-CDR/branches{/branch}","tags_url":"https://api.github.com/repos/eProsima/Fast-CDR/tags","blobs_url":"https://api.github.com/repos/eProsima/Fast-CDR/git/blobs{/sha}","git_tags_url":"https://api.github.com/repos/eProsima/Fast-CDR/git/tags{/sha}","git_refs_url":"https://api.github.com/repos/eProsima/Fast-CDR/git/refs{/sha}","trees_url":"https://api.github.com/repos/eProsima/Fast-CDR/git/trees{/sha}","statuses_url":"https://api.github.com/repos/eProsima/Fast-CDR/statuses/{sha}","languages_url":"https://api.github.com/repos/eProsima/Fast-CDR/languages","stargazers_url":"https://api.github.com/repos/eProsima/Fast-CDR/stargazers","contributors_url":"https://api.github.com/repos/eProsima/Fast-CDR/contributors","subscribers_url":"https://api.github.com/repos/eProsima/Fast-CDR/subscribers","subscription_url":"https://api.github.com/repos/eProsima/Fast-CDR/subscription","commits_url":"https://api.github.com/repos/eProsima/Fast-CDR/commits{/sha}","git_commits_url":"https://api.github.com/repos/eProsima/Fast-CDR/git/commits{/sha}","comments_url":"https://api.github.com/repos/eProsima/Fast-CDR/comments{/number}","issue_comment_url":"https://api.github.com/repos/eProsima/Fast-CDR/issues/comments{/number}","contents_url":"https://api.github.com/repos/eProsima/Fast-CDR/contents/{+path}","compare_url":"https://api.github.com/repos/eProsima/Fast-CDR/compare/{base}...{head}","merges_url":"https://api.github.com/repos/eProsima/Fast-CDR/merges","archive_url":"https://api.github.com/repos/eProsima/Fast-CDR/{archive_format}{/ref}","downloads_url":"https://api.github.com/repos/eProsima/Fast-CDR/downloads","issues_url":"https://api.github.com/repos/eProsima/Fast-CDR/issues{/number}","pulls_url":"https://api.github.com/repos/eProsima/Fast-CDR/pulls{/number}","milestones_url":"https://api.github.com/repos/eProsima/Fast-CDR/milestones{/number}","notifications_url":"https://api.github.com/repos/eProsima/Fast-CDR/notifications{?since,all,participating}","labels_url":"https://api.github.com/repos/eProsima/Fast-CDR/labels{/name}","releases_url":"https://api.github.com/repos/eProsima/Fast-CDR/releases{/id}","deployments_url":"https://api.github.com/repos/eProsima/Fast-CDR/deployments","created_at":"2014-01-14T08:35:52Z","updated_at":"2024-06-28T21:22:33Z","pushed_at":"2024-07-01T12:36:07Z","git_url":"git://github.com/eProsima/Fast-CDR.git","ssh_url":"git@github.com:eProsima/Fast-CDR.git","clone_url":"https://github.com/eProsima/Fast-CDR.git","svn_url":"https://github.com/eProsima/Fast-CDR","homepage":"","size":4380,"stargazers_count":133,"watchers_count":133,"language":"C++","has_issues":true,"has_projects":true,"has_downloads":true,"has_wiki":true,"has_pages":false,"has_discussions":true,"forks_count":99,"mirror_url":null,"archived":false,"disabled":false,"open_issues_count":5,"license":{"key":"apache-2.0","name":"Apache License 2.0","spdx_id":"Apache-2.0","url":"https://api.github.com/licenses/apache-2.0","node_id":"MDc6TGljZW5zZTI="},"allow_forking":true,"is_template":false,"web_commit_signoff_required":false,"topics":["cdr","cpp","deserialization","omg","serialization"],"visibility":"public","forks":99,"open_issues":5,"watchers":133,"default_branch":"master","permissions":{"admin":false,"maintain":false,"push":false,"triage":false,"pull":false},"temp_clone_token":"","custom_properties":{},"organization":{"login":"eProsima","id":6390783,"node_id":"MDEyOk9yZ2FuaXphdGlvbjYzOTA3ODM=","avatar_url":"https://avatars.githubusercontent.com/u/6390783?v=4","gravatar_id":"","url":"https://api.github.com/users/eProsima","html_url":"https://github.com/eProsima","followers_url":"https://api.github.com/users/eProsima/followers","following_url":"https://api.github.com/users/eProsima/following{/other_user}","gists_url":"https://api.github.com/users/eProsima/gists{/gist_id}","starred_url":"https://api.github.com/users/eProsima/starred{/owner}{/repo}","subscriptions_url":"https://api.github.com/users/eProsima/subscriptions","organizations_url":"https://api.github.com/users/eProsima/orgs","repos_url":"https://api.github.com/users/eProsima/repos","events_url":"https://api.github.com/users/eProsima/events{/privacy}","received_events_url":"https://api.github.com/users/eProsima/received_events","type":"Organization","site_admin":false},"network_count":99,"subscribers_count":20}