{"id":39840932,"node_id":"MDEwOlJlcG9zaXRvcnkzOTg0MDkzMg==","name":"googletest","full_name":"google/googletest","private":false,"owner":{"login":"google","id":1342004,"node_id":"MDEyOk9yZ2FuaXphdGlvbjEzNDIwMDQ=","avatar_url":"https://avatars.githubusercontent.com/u/1342004?v=4","gravatar_id":"","url":"https://api.github.com/users/google","html_url":"https://github.com/google","followers_url":"https://api.github.com/users/google/followers","following_url":"https://api.github.com/users/google/following{/other_user}","gists_url":"https://api.github.com/users/google/gists{/gist_id}","starred_url":"https://api.github.com/users/google/starred{/owner}{/repo}","subscriptions_url":"https://api.github.com/users/google/subscriptions","organizations_url":"https://api.github.com/users/google/orgs","repos_url":"https://api.github.com/users/google/repos","events_url":"https://api.github.com/users/google/events{/privacy}","received_events_url":"https://api.github.com/users/google/received_events","type":"Organization","site_admin":false},"html_url":"https://github.com/google/googletest","description":"GoogleTest - Google Testing and Mocking Framework","fork":false,"url":"https://api.github.com/repos/google/googletest","forks_url":"https://api.github.com/repos/google/googletest/forks","keys_url":"https://api.github.com/repos/google/googletest/keys{/key_id}","collaborators_url":"https://api.github.com/repos/google/googletest/collaborators{/collaborator}","teams_url":"https://api.github.com/repos/google/googletest/teams","hooks_url":"https://api.github.com/repos/google/googletest/hooks","issue_events_url":"https://api.github.com/repos/google/googletest/issues/events{/number}","events_url":"https://api.github.com/repos/google/googletest/events","assignees_url":"https://api.github.com/repos/google/googletest/assignees{/user}","branches_url":"https://api.github.com/repos/google/googletest/branches{/branch}","tags_url":"https://api.github.com/repos/google/googletest/tags","blobs_url":"https://api.github.com/repos/google/googletest/git/blobs{/sha}","git_tags_url":"https://api.github.com/repos/google/googletest/git/tags{/sha}","git_refs_url":"https://api.github.com/repos/google/googletest/git/refs{/sha}","trees_url":"https://api.github.com/repos/google/googletest/git/trees{/sha}","statuses_url":"https://api.github.com/repos/google/googletest/statuses/{sha}","languages_url":"https://api.github.com/repos/google/googletest/languages","stargazers_url":"https://api.github.com/repos/google/googletest/stargazers","contributors_url":"https://api.github.com/repos/google/googletest/contributors","subscribers_url":"https://api.github.com/repos/google/googletest/subscribers","subscription_url":"https://api.github.com/repos/google/googletest/subscription","commits_url":"https://api.github.com/repos/google/googletest/commits{/sha}","git_commits_url":"https://api.github.com/repos/google/googletest/git/commits{/sha}","comments_url":"https://api.github.com/repos/google/googletest/comments{/number}","issue_comment_url":"https://api.github.com/repos/google/googletest/issues/comments{/number}","contents_url":"https://api.github.com/repos/google/googletest/contents/{+path}","compare_url":"https://api.github.com/repos/google/googletest/compare/{base}...{head}","merges_url":"https://api.github.com/repos/google/googletest/merges","archive_url":"https://api.github.com/repos/google/googletest/{archive_format}{/ref}","downloads_url":"https://api.github.com/repos/google/googletest/downloads","issues_url":"https://api.github.com/repos/google/googletest/issues{/number}","pulls_url":"https://api.github.com/repos/google/googletest/pulls{/number}","milestones_url":"https://api.github.com/repos/google/googletest/milestones{/number}","notifications_url":"https://api.github.com/repos/google/googletest/notifications{?since,all,participating}","labels_url":"https://api.github.com/repos/google/googletest/labels{/name}","releases_url":"https://api.github.com/repos/google/googletest/releases{/id}","deployments_url":"https://api.github.com/repos/google/googletest/deployments","created_at":"2015-07-28T15:07:53Z","updated_at":"2024-03-23T03:07:21Z","pushed_at":"2024-03-23T04:53:38Z","git_url":"git://github.com/google/googletest.git","ssh_url":"git@github.com:google/googletest.git","clone_url":"https://github.com/google/googletest.git","svn_url":"https://github.com/google/googletest","homepage":"https://google.github.io/googletest/","size":13107,"stargazers_count":32503,"watchers_count":32503,"language":"C++","has_issues":true,"has_projects":false,"has_downloads":false,"has_wiki":false,"has_pages":true,"has_discussions":true,"forks_count":9718,"mirror_url":null,"archived":false,"disabled":false,"open_issues_count":316,"license":{"key":"bsd-3-clause","name":"BSD 3-Clause \"New\" or \"Revised\" License","spdx_id":"BSD-3-Clause","url":"https://api.github.com/licenses/bsd-3-clause","node_id":"MDc6TGljZW5zZTU="},"allow_forking":true,"is_template":false,"web_commit_signoff_required":false,"topics":[],"visibility":"public","forks":9718,"open_issues":316,"watchers":32503,"default_branch":"main","permissions":{"admin":false,"maintain":false,"push":false,"triage":false,"pull":false},"temp_clone_token":"","custom_properties":{},"organization":{"login":"google","id":1342004,"node_id":"MDEyOk9yZ2FuaXphdGlvbjEzNDIwMDQ=","avatar_url":"https://avatars.githubusercontent.com/u/1342004?v=4","gravatar_id":"","url":"https://api.github.com/users/google","html_url":"https://github.com/google","followers_url":"https://api.github.com/users/google/followers","following_url":"https://api.github.com/users/google/following{/other_user}","gists_url":"https://api.github.com/users/google/gists{/gist_id}","starred_url":"https://api.github.com/users/google/starred{/owner}{/repo}","subscriptions_url":"https://api.github.com/users/google/subscriptions","organizations_url":"https://api.github.com/users/google/orgs","repos_url":"https://api.github.com/users/google/repos","events_url":"https://api.github.com/users/google/events{/privacy}","received_events_url":"https://api.github.com/users/google/received_events","type":"Organization","site_admin":false},"network_count":9718,"subscribers_count":1210}